{
  "posts": [
    {
      "title": "새로운 데이터입니다.",
      "content": "할로",
      "createdAt": 1686105235711,
      "id": 10
    },
    {
      "title": "ㅁㅇㄹㅁㄹdpgpfkeldi",
      "content": "ㅇㅁㄹㅇㅁㄹㅁㄹdfdsf",
      "id": 11
    },
    {
      "title": "하ㅏ핳",
      "content": "후후후후",
      "createdAt": 1686124515959,
      "id": 12
    },
    {
      "title": "히히히",
      "content": "후후후후",
      "createdAt": 1686124522126,
      "id": 13
    },
    {
      "title": "쿄쿄쿄",
      "content": "쿠쿠쿠쿠",
      "createdAt": 1686124529109,
      "id": 14
    },
    {
      "title": "테스트트슽슽스",
      "content": "테스트트트트",
      "createdAt": 1686124538893,
      "id": 15
    },
    {
      "title": "캬캬캬ㅑ",
      "content": "쿄쿄쿄쿄",
      "createdAt": 1686124544026,
      "id": 16
    }
  ]
}